{
  "categories": [
    {
      "name": {
        "en": "Websites",
        "fr": "Sites web"
      },
      "projects": [
        {
          "name": "FS Thời Đại",
          "icon": "projects/folder-logma-icon.webp",
          "title": {
            "en": "FS Thời Đại - PC Game",
            "vi": "FS Thời Đại - PC Game",
            "fr": "Logma Production - Site vitrine"
          },
          "date": {
            "en": "2023 - 2 months",
            "vi": "2023 - Hiện tại",
            "fr": "2023 - 2 mois"
          },
          "componentName": "LogmaContent",
          "isFocus": false,
          "isActive": false
        },
        {
          "name": "Trụ Vương Mobi",
          "icon": "projects/folder-pangaia-icon.webp",
          "title": {
            "en": "Trụ Vương Mobi - Mobile Game",
            "vi": "Trụ Vương Mobi - Mobile Game",
            "fr": "Pangaia - Application web"
          },
          "date": {
            "en": "2025 - Current",
            "vi": "2025 - Hiện tại",
            "fr": "2023 - Actuel"
          },
          "componentName": "PangaiaContent",
          "isFocus": false,
          "isActive": false
        }
      ]
    },
    {
      "name": {
        "en": "Servers",
        "vi": "Servers",
        "fr": "Serveurs"
      },
      "projects": [
        {
          "name": "Homeserver",
          "icon": "projects/homeserver-icon.webp",
          "title": {
            "en": "Project FS Thời Đại",
            "vi": "Project FS Thời Đại",
            "fr": "Serveur d'application & stockage NAS"
          },
          "date": {
            "en": "2023 - Current",
            "vi": "2023 - Hiện tại",
            "fr": "2023 - Actuel"
          },
          "componentName": "HomeserverContent",
          "isFocus": false,
          "isActive": false
        }
      ]
    }
  ]
}
